pycountry-stubs/METADATA.toml
pycountry-stubs/__init__.pyi
pycountry-stubs/db.pyi
pycountry-stubs/py.typed
types_pycountry-24.6.0.20251119.dist-info/licenses/LICENSE
types_pycountry-24.6.0.20251119.dist-info/METADATA
types_pycountry-24.6.0.20251119.dist-info/WHEEL
types_pycountry-24.6.0.20251119.dist-info/top_level.txt
types_pycountry-24.6.0.20251119.dist-info/RECORD
